gbprocess/__init__.py
gbprocess/__main__.py
gbprocess/data.py
gbprocess/pipeline.py
gbprocess/utils.py
gbprocess/version.py
gbprocess/operations/__init__.py
gbprocess/operations/demultiplexing.py
gbprocess/operations/filtering.py
gbprocess/operations/merging.py
gbprocess/operations/operation.py
gbprocess/operations/trimming.py
gbprocess_ngs-4.0.0.post1.dist-info/LICENSE
gbprocess_ngs-4.0.0.post1.dist-info/METADATA
gbprocess_ngs-4.0.0.post1.dist-info/WHEEL
gbprocess_ngs-4.0.0.post1.dist-info/entry_points.txt
gbprocess_ngs-4.0.0.post1.dist-info/top_level.txt
gbprocess_ngs-4.0.0.post1.dist-info/RECORD
