Metadata-Version: 2.1
Name: gbprocess-ngs
Version: 4.0.0.post1
Summary: GBprocesS allows for the extraction of genomic inserts from NGS data for GBS experiments
Home-page: https://gbprocess.readthedocs.io/
Author: Dries Schaumont
Author-email: dries.schaumont@ilvo.vlaanderen.be
License: Attribution-NonCommercial-ShareAlike 4.0 International
Platform: UNKNOWN
Classifier: Programming Language :: Python :: 3
Requires-Python: >=3.7
License-File: LICENSE
Requires-Dist: BioPython (~=1.78)
Requires-Dist: cutadapt (~=3.5.0)
Provides-Extra: docs
Requires-Dist: sphinx ; extra == 'docs'
Requires-Dist: sphinx-rtd-theme ; extra == 'docs'
Requires-Dist: sphinx-tabs ; extra == 'docs'
